plover_controller/__init__.py
plover_controller/config.py
plover_controller/machine.py
plover_controller/test_util.py
plover_controller/util.py
plover_controller/assets/default_mapping.txt
plover_controller-0.0.18.dist-info/LICENSE
plover_controller-0.0.18.dist-info/METADATA
plover_controller-0.0.18.dist-info/WHEEL
plover_controller-0.0.18.dist-info/entry_points.txt
plover_controller-0.0.18.dist-info/top_level.txt
plover_controller-0.0.18.dist-info/zip-safe
plover_controller-0.0.18.dist-info/RECORD
