Metadata-Version: 2.1
Name: plover-controller
Version: 0.0.18
Summary: Controller support for Plover
Home-page: https://github.com/tadeokondrak/plover_controller
Author: Tadeo Kondrak
Author-email: me@tadeo.ca
License: GNU General Public License v2 or later (GPLv2+)
Keywords: plover plover_plugin
License-File: LICENSE
Requires-Dist: plover[gui_qt] >=4.0.0.dev10
Requires-Dist: PySDL2
Requires-Dist: pysdl2-dll ; platform_system != "Linux"
